src/__init__.py
src/aiml/__init__.py
src/daqs/__init__.py
src/demo/__init__.py
src/prep/__init__.py
src/unst/__init__.py
src/util/__init__.py
egc2delete-0.0.1.dist-info/METADATA
egc2delete-0.0.1.dist-info/WHEEL
egc2delete-0.0.1.dist-info/license
egc2delete-0.0.1.dist-info/top_level.txt
egc2delete-0.0.1.dist-info/RECORD
