Metadata-Version: 2.1
Name: egc2delete
Version: 0.0.1
Summary: A small example package from EGC
Home-page: https://github.com/EgC-Team/EngineeringGoesCloud
Author: EgC-Team
Author-email: mail@engineering-goes-cloud.de
License: UNKNOWN
Platform: UNKNOWN
Classifier: Programming Language :: Python :: 3
Classifier: License :: OSI Approved :: MIT License
Classifier: Operating System :: OS Independent
Requires-Python: >=3.7
Requires-Dist: numpy
Requires-Dist: xlrd
Provides-Extra: all
Requires-Dist: bitstruct ; extra == 'all'
Requires-Dist: pandas ; extra == 'all'
Requires-Dist: tensorflow ; extra == 'all'
Requires-Dist: keras ; extra == 'all'
Requires-Dist: seaborn ; extra == 'all'
Requires-Dist: tsfresh ; extra == 'all'
Requires-Dist: requests ; extra == 'all'
Requires-Dist: asammdf ; extra == 'all'
Requires-Dist: flask ; extra == 'all'
Requires-Dist: scipy ; extra == 'all'
Provides-Extra: analysisdrvcyc
Requires-Dist: asammdf ; extra == 'analysisdrvcyc'
Requires-Dist: bitstruct ; extra == 'analysisdrvcyc'
Requires-Dist: pandas ; extra == 'analysisdrvcyc'
Provides-Extra: modelingann
Requires-Dist: keras ; extra == 'modelingann'
Requires-Dist: pandas ; extra == 'modelingann'
Requires-Dist: scipy ; extra == 'modelingann'
Requires-Dist: seaborn ; extra == 'modelingann'
Requires-Dist: tensorflow ; extra == 'modelingann'
Requires-Dist: tsfresh ; extra == 'modelingann'
Provides-Extra: servicedrvcyc
Requires-Dist: flask ; extra == 'servicedrvcyc'
Requires-Dist: requests ; extra == 'servicedrvcyc'
